zdppy_log/__init__.py
zdppy_log/_asyncio_loop.py
zdppy_log/_better_exceptions.py
zdppy_log/_colorama.py
zdppy_log/_colorizer.py
zdppy_log/_contextvars.py
zdppy_log/_ctime_functions.py
zdppy_log/_datetime.py
zdppy_log/_defaults.py
zdppy_log/_error_interceptor.py
zdppy_log/_file_sink.py
zdppy_log/_filters.py
zdppy_log/_get_frame.py
zdppy_log/_handler.py
zdppy_log/_locks_machinery.py
zdppy_log/_logger.py
zdppy_log/_recattrs.py
zdppy_log/_simple_sinks.py
zdppy_log/_string_parsers.py
zdppy_log/colorama/__init__.py
zdppy_log/colorama/ansi.py
zdppy_log/colorama/ansitowin32.py
zdppy_log/colorama/initialise.py
zdppy_log/colorama/win32.py
zdppy_log/colorama/winterm.py
zdppy_log/level.py
zdppy_log/logger.py
zdppy_log/win32_setctime.py
zdppy_log-0.2.1.dist-info/METADATA
zdppy_log-0.2.1.dist-info/WHEEL
zdppy_log-0.2.1.dist-info/RECORD
