Metadata-Version: 2.1
Name: zdppy-log
Version: 0.2.1
Summary: Python操作日志的底层核心框架
Author: 张大鹏
Author-email: 1156956636@qq.com
Requires-Python: >=3.8,<4.0
Classifier: Programming Language :: Python :: 3
Classifier: Programming Language :: Python :: 3.8
Classifier: Programming Language :: Python :: 3.9
Classifier: Programming Language :: Python :: 3.10
Classifier: Programming Language :: Python :: 3.11
Classifier: Programming Language :: Python :: 3.12
